nonebot/adapters/wxmp/__init__.py
nonebot/adapters/wxmp/adapter.py
nonebot/adapters/wxmp/bot.py
nonebot/adapters/wxmp/bot.pyi
nonebot/adapters/wxmp/config.py
nonebot/adapters/wxmp/event.py
nonebot/adapters/wxmp/exception.py
nonebot/adapters/wxmp/file.py
nonebot/adapters/wxmp/message.py
nonebot/adapters/wxmp/secret.py
nonebot/adapters/wxmp/store.py
nonebot/adapters/wxmp/utils.py
nonebot_adapter_wxmp-0.1.7.dist-info/LICENSE
nonebot_adapter_wxmp-0.1.7.dist-info/METADATA
nonebot_adapter_wxmp-0.1.7.dist-info/WHEEL
nonebot_adapter_wxmp-0.1.7.dist-info/top_level.txt
nonebot_adapter_wxmp-0.1.7.dist-info/RECORD
