Metadata-Version: 2.2
Name: nonebot-adapter-wxmp
Version: 0.1.7
Summary: Nonebot2 Adapter for Weixin Official Accounts Platform
Author-email: YangRucheng <admin@yangrucheng.top>
License: MIT
Project-URL: homepage, https://github.com/YangRucheng/nonebot-adapter-wxmp
Project-URL: repository, https://github.com/YangRucheng/nonebot-adapter-wxmp
Requires-Python: >=3.9
License-File: LICENSE
Requires-Dist: nonebot2>=2.3.0
Requires-Dist: xmltodict>=0.14.0
